greenglacier.py
GreenGlacier-1.0.0.dist-info/DESCRIPTION.rst
GreenGlacier-1.0.0.dist-info/METADATA
GreenGlacier-1.0.0.dist-info/RECORD
GreenGlacier-1.0.0.dist-info/WHEEL
GreenGlacier-1.0.0.dist-info/metadata.json
GreenGlacier-1.0.0.dist-info/top_level.txt
